LICENSE.txt
README.md
setup.py
woe_iv_bin/__init__.py
woe_iv_bin/categorical_woe.py
woe_iv_bin/continuous_binning_woe.py
woe_iv_bin.egg-info/PKG-INFO
woe_iv_bin.egg-info/SOURCES.txt
woe_iv_bin.egg-info/dependency_links.txt
woe_iv_bin.egg-info/requires.txt
woe_iv_bin.egg-info/top_level.txt