Metadata-Version: 2.1
Name: woe_iv_bin
Version: 0.1.2
Summary: A Python Library for WoE, IV Calculation, and Continuous Binning Optimization.
Home-page: https://github.com/knowusuboaky/woe-iv-bin
Author: Kwadwo Daddy Nyame Owusu - Boakye
Author-email: kwadwo.owusuboakye@outlook.com
Keywords: woe,iv,binning,feature-engineering,weight of evidence,optimization,scoring,predictive-modeling
Classifier: Development Status :: 3 - Alpha
Classifier: Intended Audience :: Developers
Classifier: Topic :: Software Development :: Build Tools
Classifier: License :: OSI Approved :: MIT License
Classifier: Programming Language :: Python :: 3
Classifier: Programming Language :: Python :: 3.6
Classifier: Programming Language :: Python :: 3.7
Classifier: Programming Language :: Python :: 3.8
Classifier: Programming Language :: Python :: 3.9
Classifier: Programming Language :: Python :: 3.10
Classifier: Programming Language :: Python :: 3.11
Classifier: Programming Language :: Python :: 3.12
Requires-Python: >=3.6
License-File: LICENSE.txt
Requires-Dist: pandas>=1.1.5
Requires-Dist: numpy>=1.19.5
Requires-Dist: matplotlib>=3.3.3
Requires-Dist: seaborn>=0.11.1
Requires-Dist: pandas>=1.0.0
